image_scraper/__init__.py
image_scraper/scraper.py
image_scraper_quality-0.1.0.dist-info/licenses/LICENSE
image_scraper_quality-0.1.0.dist-info/METADATA
image_scraper_quality-0.1.0.dist-info/WHEEL
image_scraper_quality-0.1.0.dist-info/entry_points.txt
image_scraper_quality-0.1.0.dist-info/top_level.txt
image_scraper_quality-0.1.0.dist-info/RECORD
